setup.py
bngl/__init__.py
bngl/activation.py
bngl/graph.py
bngl/layer.py
bngl/loss.py
bngl/operation.py
bngl.egg-info/PKG-INFO
bngl.egg-info/SOURCES.txt
bngl.egg-info/dependency_links.txt
bngl.egg-info/requires.txt
bngl.egg-info/top_level.txt