Metadata-Version: 1.0
Name: bngl
Version: 0.1.1
Summary: Bstadt's NeuroGraph Library
Home-page: https://github.com/bstadt/bngl.git
Author: Brandon Duderstadt
Author-email: UNKNOWN
License: UNKNOWN
Platform: UNKNOWN
